docparser/__init__.py
docparser/_tesseract_langs.py
docparser/parser.py
docparser/pipeline_clip.py
docparser/pipeline_dict.py
docparser/sample.py
docparser/utils.py
docparser/data/__init__.py
docparser/data/tesseract_langs.py
tests/__init__.py
tests/sample_test.py
samagra_docparser-0.1.2.dist-info/METADATA
samagra_docparser-0.1.2.dist-info/WHEEL
samagra_docparser-0.1.2.dist-info/top_level.txt
samagra_docparser-0.1.2.dist-info/RECORD
